qapla/__init__.py
qapla/app.py
qapla/controller.py
qapla/database.py
qapla/driver.py
qapla/routing.py
qapla/settings.py
qapla/testing.py
qapla/utils.py
qapla/database/__init__.py
qapla/database/application.py
qapla/database/database.py
qapla/database/decorators.py
qapla/database/env.py
qapla/database/exceptions.py
qapla/database/plugin.py
qapla/database/request.py
qapla/database/testing.py
qapla/database/tests/__init__.py
qapla/database/tests/test_application.py
qapla/database/tests/test_database.py
qapla/database/tests/test_decorators.py
qapla/database/tests/test_env.py
qapla/database/tests/test_exceptions.py
qapla/database/tests/test_plugin.py
qapla/database/tests/test_request.py
qapla/tests/__init__.py
qapla/tests/test_app.py
qapla/tests/test_controller.py
qapla/tests/test_db.py
qapla/tests/test_driver.py
qapla/tests/test_routing.py
qapla/tests/test_settings.py
qapla-0.4.0.dist-info/DESCRIPTION.rst
qapla-0.4.0.dist-info/METADATA
qapla-0.4.0.dist-info/RECORD
qapla-0.4.0.dist-info/WHEEL
qapla-0.4.0.dist-info/metadata.json
qapla-0.4.0.dist-info/top_level.txt
