Metadata-Version: 2.0
Name: qapla
Version: 0.4.0
Summary: UNKNOWN
Home-page: UNKNOWN
Author: UNKNOWN
Author-email: UNKNOWN
License: Apache License 2.0
Platform: UNKNOWN
Requires-Dist: PyYAML (>=3.12)
Requires-Dist: colander (>=1.3.3)
Requires-Dist: morfdict (>=0.4.6)
Requires-Dist: pyramid (>=1.9)
